Metadata-Version: 2.1
Name: bulksmsng
Version: 1.0.0
Summary: The BulkSMSNigeria API Wrapper is a Python library that provides a convenient interface for sending SMS messages
Home-page: https://github.com/emmyvera/bulksmsng
Author: Oluwaloni Emmanuel
Author-email: emmyvera01@gmail.com
License: MIT
Keywords: SMS,Nigeria,BulkSMS,Bulk SMS Nigeria,bulk sms
Classifier: Programming Language :: Python :: 3
Classifier: License :: OSI Approved :: MIT License
Classifier: Operating System :: OS Independent
Requires-Python: >=3.6
